odoo/addons/fieldservice_location_builder/README.rst
odoo/addons/fieldservice_location_builder/__init__.py
odoo/addons/fieldservice_location_builder/__manifest__.py
odoo/addons/fieldservice_location_builder/i18n/de.po
odoo/addons/fieldservice_location_builder/i18n/es.po
odoo/addons/fieldservice_location_builder/i18n/es_AR.po
odoo/addons/fieldservice_location_builder/i18n/es_CL.po
odoo/addons/fieldservice_location_builder/i18n/fieldservice_location_builder.pot
odoo/addons/fieldservice_location_builder/i18n/it.po
odoo/addons/fieldservice_location_builder/i18n/pt_BR.po
odoo/addons/fieldservice_location_builder/readme/CONTRIBUTORS.rst
odoo/addons/fieldservice_location_builder/readme/DESCRIPTION.rst
odoo/addons/fieldservice_location_builder/readme/ROADMAP.rst
odoo/addons/fieldservice_location_builder/readme/USAGE.rst
odoo/addons/fieldservice_location_builder/security/ir.model.access.csv
odoo/addons/fieldservice_location_builder/static/description/icon.png
odoo/addons/fieldservice_location_builder/static/description/index.html
odoo/addons/fieldservice_location_builder/tests/__init__.py
odoo/addons/fieldservice_location_builder/tests/test_fsm_location_builder.py
odoo/addons/fieldservice_location_builder/wizard/__init__.py
odoo/addons/fieldservice_location_builder/wizard/fsm_location_builder_wizard.py
odoo/addons/fieldservice_location_builder/wizard/fsm_location_builder_wizard.xml
odoo/addons/fieldservice_location_builder/wizard/fsm_location_level.py
odoo/addons/fieldservice_location_builder/wizard/fsm_location_level.xml
odoo14_addon_fieldservice_location_builder-14.0.1.0.1.dist-info/METADATA
odoo14_addon_fieldservice_location_builder-14.0.1.0.1.dist-info/WHEEL
odoo14_addon_fieldservice_location_builder-14.0.1.0.1.dist-info/top_level.txt
odoo14_addon_fieldservice_location_builder-14.0.1.0.1.dist-info/RECORD
